vxlib/__init__.py
vxlib/color.py
vxlib/log.py
vxlib/poller.py
vxlib/types.py
vxlib/utils.py
vxlib/vec.py
vxlib-0.1.0.dist-info/WHEEL
vxlib-0.1.0.dist-info/METADATA
vxlib-0.1.0.dist-info/RECORD
