Metadata-Version: 2.4
Name: vxlib
Version: 0.1.0
Summary: Shared types and utilities for the Voxel microscopy platform
Keywords: voxel,microscopy,utilities,types
Author: Walter Mwaniki
Author-email: Walter Mwaniki <walter.g.mwaniki@gmail.com>
License-Expression: MIT
Classifier: Development Status :: 3 - Alpha
Classifier: Intended Audience :: Science/Research
Classifier: Topic :: Scientific/Engineering
Requires-Dist: numpy>=2.0
Requires-Dist: pydantic>=2.0
Requires-Dist: rich>=14.0.0 ; extra == 'rich'
Requires-Python: >=3.13
Project-URL: Repository, https://github.com/AllenNeuralDynamics/voxel
Project-URL: Issues, https://github.com/AllenNeuralDynamics/voxel/issues
Provides-Extra: rich
